BT_SQLAlchemy_DB_ORM_Template/App.py
BT_SQLAlchemy_DB_ORM_Template/Manage.py
BT_SQLAlchemy_DB_ORM_Template/__init__.py
BT_SQLAlchemy_DB_ORM_Template/BlueWhale/AppStart/AppStart.py
BT_SQLAlchemy_DB_ORM_Template/BlueWhale/Initializer/Initializer.py
BT_SQLAlchemy_DB_ORM_Template/BlueWhale/MigrationFolderOS/MigrationFolderOS.py
BT_SQLAlchemy_DB_ORM_Template/Entity/DbConfig/DbConfig.py
BT_SQLAlchemy_DB_ORM_Template/Entity/ModelBase/ModelBase.py
BT_SQLAlchemy_DB_ORM_Template/Entity/Packages/EntityModels.py
BT_SQLAlchemy_DB_ORM_Template/Entity/Table/AuthenticationLogs.py
BT_SQLAlchemy_DB_ORM_Template/Entity/Table/Authentications.py
BT_SQLAlchemy_DB_ORM_Template/Entity/Table/Users.py
BT_SQLAlchemy_DB_ORM_Template/Utils/GeneralLists.py
BT_SQLAlchemy_DB_ORM_Template-1.0.0.dist-info/LICENSE
BT_SQLAlchemy_DB_ORM_Template-1.0.0.dist-info/METADATA
BT_SQLAlchemy_DB_ORM_Template-1.0.0.dist-info/WHEEL
BT_SQLAlchemy_DB_ORM_Template-1.0.0.dist-info/top_level.txt
BT_SQLAlchemy_DB_ORM_Template-1.0.0.dist-info/RECORD
